jener/__main__.py
jener/model/__init__.py
jener/model/base.py
jener/model/ner.py
jener/model/ner_crf.py
jener/model/loss/__init__.py
jener/model/loss/asymmetric.py
jener/model/loss/multi_cross_entropy.py
jener/model/loss/twoway.py
jener/model/loss/weigted_bce_wigh_logits.py
jener/model/utils/__init__.py
jener/model/utils/crf.py
jener/utils/array.py
jener/utils/data.py
jener-1.0.6.dist-info/METADATA
jener-1.0.6.dist-info/WHEEL
jener-1.0.6.dist-info/top_level.txt
jener-1.0.6.dist-info/RECORD
