Metadata-Version: 2.1
Name: jener
Version: 1.0.6
Summary: Japanese Extended Named Entity Recognizer
Home-page: https://github.com/k141303/JENER
Author: k141303
Author-email: kouta.nakayama@gmail.com
License: UNKNOWN
Download-URL: https://github.com/k141303/JENER
Platform: UNKNOWN
Requires-Dist: torch (>=1.13.0)
Requires-Dist: hydra-core (>=1.2.0)
Requires-Dist: tqdm (>=4.64.1)
Requires-Dist: liat-ml-roberta
Requires-Dist: torch-struct
Requires-Dist: transformers (>=4.22.1)
